lancedb-0.26.0.dist-info/METADATA
lancedb-0.26.0.dist-info/WHEEL
lancedb-0.26.0.dist-info/licenses/LICENSE
lancedb/__init__.py
lancedb/_lancedb.abi3.so
lancedb/_lancedb.pyi
lancedb/arrow.py
lancedb/background_loop.py
lancedb/common.py
lancedb/conftest.py
lancedb/context.py
lancedb/db.py
lancedb/dependencies.py
lancedb/embeddings/__init__.py
lancedb/embeddings/base.py
lancedb/embeddings/bedrock.py
lancedb/embeddings/cohere.py
lancedb/embeddings/colpali.py
lancedb/embeddings/gemini_text.py
lancedb/embeddings/gte.py
lancedb/embeddings/gte_mlx_model.py
lancedb/embeddings/imagebind.py
lancedb/embeddings/instructor.py
lancedb/embeddings/jinaai.py
lancedb/embeddings/ollama.py
lancedb/embeddings/open_clip.py
lancedb/embeddings/openai.py
lancedb/embeddings/registry.py
lancedb/embeddings/sentence_transformers.py
lancedb/embeddings/siglip.py
lancedb/embeddings/transformers.py
lancedb/embeddings/utils.py
lancedb/embeddings/voyageai.py
lancedb/embeddings/watsonx.py
lancedb/exceptions.py
lancedb/fts.py
lancedb/index.py
lancedb/integrations/__init__.py
lancedb/integrations/pyarrow.py
lancedb/io.py
lancedb/merge.py
lancedb/namespace.py
lancedb/namespace_utils.py
lancedb/permutation.py
lancedb/pydantic.py
lancedb/query.py
lancedb/remote/__init__.py
lancedb/remote/db.py
lancedb/remote/errors.py
lancedb/remote/header.py
lancedb/remote/table.py
lancedb/rerankers/__init__.py
lancedb/rerankers/answerdotai.py
lancedb/rerankers/base.py
lancedb/rerankers/cohere.py
lancedb/rerankers/colbert.py
lancedb/rerankers/cross_encoder.py
lancedb/rerankers/jinaai.py
lancedb/rerankers/linear_combination.py
lancedb/rerankers/mrr.py
lancedb/rerankers/openai.py
lancedb/rerankers/rrf.py
lancedb/rerankers/util.py
lancedb/rerankers/voyageai.py
lancedb/schema.py
lancedb/table.py
lancedb/types.py
lancedb/util.py
lancedb-0.26.0.dist-info/RECORD
