Metadata-Version: 2.4
Name: lancedb
Version: 0.26.0
Classifier: Development Status :: 3 - Alpha
Classifier: Environment :: Console
Classifier: Intended Audience :: Science/Research
Classifier: License :: OSI Approved :: Apache Software License
Classifier: Operating System :: OS Independent
Classifier: Programming Language :: Python
Classifier: Programming Language :: Python :: 3
Classifier: Programming Language :: Python :: 3 :: Only
Classifier: Programming Language :: Python :: 3.9
Classifier: Programming Language :: Python :: 3.10
Classifier: Programming Language :: Python :: 3.11
Classifier: Programming Language :: Python :: 3.12
Classifier: Topic :: Scientific/Engineering
Requires-Dist: deprecation
Requires-Dist: numpy
Requires-Dist: overrides>=0.7 ; python_full_version < '3.12'
Requires-Dist: packaging
Requires-Dist: pyarrow>=16
Requires-Dist: pydantic>=1.10
Requires-Dist: tqdm>=4.27.0
Requires-Dist: lance-namespace>=0.3.2
Requires-Dist: pylance>=1.0.0b14 ; extra == 'pylance'
Requires-Dist: aiohttp ; extra == 'tests'
Requires-Dist: boto3 ; extra == 'tests'
Requires-Dist: pandas>=1.4 ; extra == 'tests'
Requires-Dist: pytest ; extra == 'tests'
Requires-Dist: pytest-mock ; extra == 'tests'
Requires-Dist: pytest-asyncio ; extra == 'tests'
Requires-Dist: duckdb ; extra == 'tests'
Requires-Dist: pytz ; extra == 'tests'
Requires-Dist: polars>=0.19,<=1.3.0 ; extra == 'tests'
Requires-Dist: tantivy ; extra == 'tests'
Requires-Dist: pyarrow-stubs ; extra == 'tests'
Requires-Dist: pylance>=1.0.0b14 ; extra == 'tests'
Requires-Dist: requests ; extra == 'tests'
Requires-Dist: datafusion ; extra == 'tests'
Requires-Dist: ruff ; extra == 'dev'
Requires-Dist: pre-commit ; extra == 'dev'
Requires-Dist: pyright ; extra == 'dev'
Requires-Dist: typing-extensions>=4.0.0 ; python_full_version < '3.11' and extra == 'dev'
Requires-Dist: mkdocs ; extra == 'docs'
Requires-Dist: mkdocs-jupyter ; extra == 'docs'
Requires-Dist: mkdocs-material ; extra == 'docs'
Requires-Dist: mkdocstrings-python ; extra == 'docs'
Requires-Dist: torch ; extra == 'clip'
Requires-Dist: pillow ; extra == 'clip'
Requires-Dist: open-clip-torch ; extra == 'clip'
Requires-Dist: torch ; extra == 'siglip'
Requires-Dist: pillow ; extra == 'siglip'
Requires-Dist: transformers>=4.41.0 ; extra == 'siglip'
Requires-Dist: sentencepiece ; extra == 'siglip'
Requires-Dist: requests>=2.31.0 ; extra == 'embeddings'
Requires-Dist: openai>=1.6.1 ; extra == 'embeddings'
Requires-Dist: sentence-transformers ; extra == 'embeddings'
Requires-Dist: torch ; extra == 'embeddings'
Requires-Dist: pillow ; extra == 'embeddings'
Requires-Dist: open-clip-torch ; extra == 'embeddings'
Requires-Dist: cohere ; extra == 'embeddings'
Requires-Dist: colpali-engine>=0.3.10 ; extra == 'embeddings'
Requires-Dist: huggingface-hub ; extra == 'embeddings'
Requires-Dist: instructorembedding ; extra == 'embeddings'
Requires-Dist: google-generativeai ; extra == 'embeddings'
Requires-Dist: boto3>=1.28.57 ; extra == 'embeddings'
Requires-Dist: awscli>=1.29.57 ; extra == 'embeddings'
Requires-Dist: botocore>=1.31.57 ; extra == 'embeddings'
Requires-Dist: ibm-watsonx-ai>=1.1.2 ; python_full_version >= '3.10' and extra == 'embeddings'
Requires-Dist: ollama>=0.3.0 ; extra == 'embeddings'
Requires-Dist: sentencepiece ; extra == 'embeddings'
Requires-Dist: adlfs>=2024.2.0 ; extra == 'azure'
Provides-Extra: pylance
Provides-Extra: tests
Provides-Extra: dev
Provides-Extra: docs
Provides-Extra: clip
Provides-Extra: siglip
Provides-Extra: embeddings
Provides-Extra: azure
License-File: LICENSE
Summary: lancedb
Keywords: data-format,data-science,machine-learning,arrow,data-analytics
Author-email: LanceDB Devs <dev@lancedb.com>
Requires-Python: >=3.9
Project-URL: repository, https://github.com/lancedb/lancedb
